MANIFEST.in
README.md
setup.py
py_raft.egg-info/PKG-INFO
py_raft.egg-info/SOURCES.txt
py_raft.egg-info/dependency_links.txt
py_raft.egg-info/top_level.txt
raft/__init__.py
raft/bijectivemap.py
raft/client.py
raft/log.py
raft/server.py
raft/store.py
raft/tcp.py
raft/udp.py
raft/version.txt