Metadata-Version: 1.1
Name: py-raft
Version: 0.0.1
Summary: The RAFT Consensus Algorithm
Home-page: UNKNOWN
Author: Toby Burress
Author-email: kurin@delete.org
License: UNKNOWN
Platform: UNKNOWN
Classifier: Development Status :: 1 - Planning
Classifier: License :: Public Domain
Classifier: Programming Language :: Python :: 2.6
Classifier: Programming Language :: Python :: 2.7
